Combinational Circuits/Full Subtractor/fullsub.v
module full_sub(Sub,Bout,A,B,Bin);
    input A,B,Bin;
    output Sub, Bout;
    assign Sub = A^B^Bin;
    assign Bout = ((~A)&Bin) | (B&Bin) | ((~A)&B);
endmodule

Combinational Circuits/Full Subtractor/fullsub_tb.v
`timescale 1ns/1ns
`include "fullsub.v"
module full_sub_tb;
    reg A,B,Cin;
    wire Sub,Bout;
    full_sub uut(Sub,Bout,A,B,Cin);
    initial begin
        $display("A B Cin | Sub Bout");
        $monitor("%b %b %b |  %b   %b",A,B,Cin,Sub,Bout);
        A=0; B=0; Cin=0; #10;
        A=0; B=1; Cin=0; #10;
        A=1; B=0; Cin=0; #10;
        A=1; B=1; Cin=0; #10;
        A=0; B=0; Cin=1; #10;
        A=0; B=1; Cin=1; #10;
        A=1; B=0; Cin=1; #10;
        A=1; B=1; Cin=1; #10;
        $finish;
    end
    initial begin
        $dumpfile("full_sub_tb.vcd");
        $dumpvars(0,full_sub_tb);
    end
endmodule

Combinational Circuits/Full Subtractor/full_sub_tb.vcd
$date
	Tue Dec 30 22:35:31 2025
$end
$version
	Icarus Verilog
$end
$timescale
	1ns
$end
$scope module full_sub_tb $end
$var wire 1 ! Sub $end
$var wire 1 " Bout $end
$var reg 1 # A $end
$var reg 1 $ B $end
$var reg 1 % Cin $end
$scope module uut $end
$var wire 1 # A $end
$var wire 1 $ B $end
$var wire 1 % Bin $end
$var wire 1 " Bout $end
$var wire 1 ! Sub $end
$upscope $end
$upscope $end
$enddefinitions $end
$comment Show the parameter values. $end
$dumpall
$end
#0
$dumpvars
0%
0$
0#
0"
0!
$end
#10
1!
1"
1$
#20
0"
0$
1#
#30
0!
1$
#40
1"
1!
1%
0$
0#
#50
0!
1$
#60
0"
0$
1#
#70
1"
1!
1$
