Combinational Circuits/Tri_State_Buffer/Tristate_buffer.v
module tri_state_buffer(
    input x,y,sel,
    output tri f
);
    bufif0(f,x,sel);
    bufif1(f,y,sel);
endmodule

Combinational Circuits/Tri_State_Buffer/Tristate_buffer_tb.v
 `timescale 1ns/1ps
 `include "Tristate_buffer.v"
 module Tristate_buffer_tb;
    reg a,b,sel;
    wire f;
    tri_state_buffer uut(
        .x(a),
        .y(b),
        .sel(sel),
        .f(f)
    );
    initial begin
        a=0;b=0;sel=0;
        for(integer i=0;i<10;i=i+1) begin
            a= $random & 1;
            b= $random & 1;
            sel= $random & 1;
            #10;
        end
        #10
        $finish;
    end
    initial begin
        $monitor("At time %t: a=%b, b=%b, sel=%b, f=%b",$time,a,b,sel,f);
    end
    initial begin
        $dumpfile("Tristate_buffer_tb.vcd");
        $dumpvars(0,Tristate_buffer_tb);
    end
endmodule

Combinational Circuits/Tri_State_Buffer/Tristate_buffer_tb.vcd
$date
	Sat Mar 21 18:31:06 2026
$end
$version
	Icarus Verilog
$end
$timescale
	1ps
$end
$scope module Tristate_buffer_tb $end
$var wire 1 ! f $end
$var reg 1 " a $end
$var reg 1 # b $end
$var reg 1 $ sel $end
$scope module uut $end
$var wire 1 ! f $end
$var wire 1 $ sel $end
$var wire 1 " x $end
$var wire 1 # y $end
$upscope $end
$scope begin $ivl_for_loop0 $end
$var integer 32 % i [31:0] $end
$upscope $end
$upscope $end
$enddefinitions $end
$comment Show the parameter values. $end
$dumpall
$end
#0
$dumpvars
b0 %
1$
1#
0"
1!
$end
#10000
1"
b1 %
#20000
0!
0#
b10 %
#30000
b11 %
#40000
b100 %
#50000
0$
0!
1#
0"
b101 %
#60000
1!
1"
b110 %
#70000
0#
b111 %
#80000
1#
0!
0"
b1000 %
#90000
1$
1!
1"
b1001 %
#100000
b1010 %
