Combinational Circuits/Full Adder/fulladder.v
module full_adder(Sum,Cout,A,B,Cin);
    input A,B,Cin;
    output Sum,Cout;
    assign Sum = A^B^Cin;
    assign Cout = (A&B) | (B&Cin) | (A&Cin);
endmodule

Combinational Circuits/Ripple Carry Adder/fulladder_tb.v
`timescale 1ns/1ns
`include "fulladder.v"
module full_adder_tb;
    reg A,B,Cin;
    wire Sum,Cout;
    full_adder uut(Sum,Cout,A,B,Cin);
    initial begin
        $display("A B Cin | Sum Cout");
        $monitor("%b %b %b |  %b   %b",A,B,Cin,Sum,Cout);
        A=0; B=0; Cin=0; #10;
        A=0; B=1; Cin=0; #10;
        A=1; B=0; Cin=0; #10;
        A=1; B=1; Cin=0; #10;
        A=0; B=0; Cin=1; #10;
        A=0; B=1; Cin=1; #10;
        A=1; B=0; Cin=1; #10;
        A=1; B=1; Cin=1; #10;
        $finish;
    end
    initial begin
        $dumpfile("full_adder_tb.vcd");
        $dumpvars(0,full_adder_tb);
    end
endmodule

Combinational Circuits/Full Adder/full_adder_tb.vcd
$date
	Tue Dec 30 22:29:26 2025
$end
$version
	Icarus Verilog
$end
$timescale
	1ns
$end
$scope module full_adder_tb $end
$var wire 1 ! Sum $end
$var wire 1 " Cout $end
$var reg 1 # A $end
$var reg 1 $ B $end
$var reg 1 % Cin $end
$scope module uut $end
$var wire 1 # A $end
$var wire 1 $ B $end
$var wire 1 % Cin $end
$var wire 1 " Cout $end
$var wire 1 ! Sum $end
$upscope $end
$upscope $end
$enddefinitions $end
$comment Show the parameter values. $end
$dumpall
$end
#0
$dumpvars
0%
0$
0#
0"
0!
$end
#10
1!
1$
#20
0$
1#
#30
1"
0!
1$
#40
0"
1!
1%
0$
0#
#50
1"
0!
1$
#60
0$
1#
#70
1!
1$
