Finite State Machines/Three_floor_Elevator/Elevator.v
module Elevator(
    input clk,
    input rst,
    input ra,
    input rb,
    input rc,
    output reg [1:0] floor
);
parameter A  = 2'b00,
          BU = 2'b01,
          BD = 2'b10,
          C  = 2'b11;

reg [1:0] state;

always @(posedge clk) begin
    if (rst)
        state <= A;
    else begin
        case (state)

            A: begin
                if (ra)
                    state <= A;
                else if (rb)
                    state <= BU;
                else if (rc)
                    state <= C;
                else
                    state <= A;
            end

            BU: begin
                if (rb)
                    state <= BU;
                else if (rc)
                    state <= C;
                else if (ra)
                    state <= A;
                else
                    state <= BU;
            end

            BD: begin
                if (rb)
                    state <= BD;
                else if (rc)
                    state <= C;
                else if (ra)
                    state <= A;
                else
                    state <= BD;
            end

            C: begin
                if (rc)
                    state <= C;
                else if (rb)
                    state <= BD;
                else if (ra)
                    state <= A;
                else
                    state <= C;
            end

            default: state <= A;

        endcase
    end
end

always @(*) begin
    case (state)
        A: floor = 2'b00;
        BU, BD: floor = 2'b01;
        C: floor = 2'b10;
        default: floor = 2'b00;
    endcase
end
endmodule

Finite State Machines/Three_floor_Elevator/Elevator_tb.v
`timescale 1ns/1ps
`include "Elevator.v"
module Elevator_tb;
reg clk = 0;
reg rst;
reg ra = 0;
reg rb = 0;
reg rc = 0;
wire [1:0] floor;
Elevator DUT (clk, rst, ra, rb, rc, floor);
always #5 clk = ~clk;
initial begin
    rst = 1;
    #10 rst = 0;
end
initial begin
    $display("Time\tclk rst ra rb rc | floor");
    $monitor("%0t\t%b   %b   %b  %b  %b | %b",
              $time, clk, rst, ra, rb, rc, floor);

    repeat (2) @(posedge clk);

    repeat (5) begin
        {ra, rb, rc} = $random;
        @(posedge clk);

        {ra, rb, rc} = 3'b000;
        repeat (2) @(posedge clk);
    end

    $finish;
end
initial begin
    $dumpfile("Elevator_tb.vcd");
    $dumpvars(0, Elevator_tb);
end
endmodule

Finite State Machines/Three_floor_Elevator/Elevator_tb.vcd
$date
	Sun Mar 22 22:44:40 2026
$end
$version
	Icarus Verilog
$end
$timescale
	1ps
$end
$scope module Elevator_tb $end
$var wire 2 ! floor [1:0] $end
$var reg 1 " clk $end
$var reg 1 # ra $end
$var reg 1 $ rb $end
$var reg 1 % rc $end
$var reg 1 & rst $end
$scope module DUT $end
$var wire 1 " clk $end
$var wire 1 # ra $end
$var wire 1 $ rb $end
$var wire 1 % rc $end
$var wire 1 & rst $end
$var parameter 2 ' A $end
$var parameter 2 ( BD $end
$var parameter 2 ) BU $end
$var parameter 2 * C $end
$var reg 2 + floor [1:0] $end
$var reg 2 , state [1:0] $end
$upscope $end
$upscope $end
$enddefinitions $end
$comment Show the parameter values. $end
$dumpall
b11 *
b1 )
b10 (
b0 '
$end
#0
$dumpvars
bx ,
bx +
1&
0%
0$
0#
0"
bx !
$end
#5000
b0 !
b0 +
b0 ,
1"
#10000
0"
0&
#15000
1#
1"
#20000
0"
#25000
0#
1"
#30000
0"
#35000
1"
#40000
0"
#45000
b10 !
b10 +
b11 ,
1%
1"
#50000
0"
#55000
0%
1"
#60000
0"
#65000
1"
#70000
0"
#75000
1%
1"
#80000
0"
#85000
0%
1"
#90000
0"
#95000
1"
#100000
0"
#105000
1$
1%
1"
#110000
0"
#115000
0$
0%
1"
#120000
0"
#125000
1"
#130000
0"
#135000
1#
1%
1"
#140000
0"
#145000
0#
0%
1"
#150000
0"
#155000
1"
#160000
0"
#165000
1#
1%
1"
#170000
0"
#175000
0#
0%
1"
#180000
0"
#185000
1"
#190000
0"
#195000
1#
1%
1"
#200000
0"
#205000
0#
0%
1"
#210000
0"
#215000
1"
#220000
0"
#225000
b1 !
b1 +
b10 ,
1$
1"
#230000
0"
#235000
0$
1"
#240000
0"
#245000
1"
#250000
0"
#255000
1%
1"
#260000
0"
#265000
0%
1"
#270000
0"
#275000
1"
#280000
0"
#285000
b10 !
b10 +
b11 ,
1#
1%
1"
#290000
0"
#295000
0#
0%
1"
#300000
0"
#305000
1"
#310000
0"
#315000
1#
1$
1"
#320000
0"
#325000
0#
0$
1"
#330000
0"
#335000
1"
#340000
0"
#345000
1#
1%
1"
#350000
0"
#355000
0#
0%
1"
#360000
0"
#365000
1"
#370000
0"
#375000
1#
1%
1"
#380000
0"
#385000
0#
0%
1"
#390000
0"
#395000
1"
#400000
0"
#405000
b0 !
b0 +
b0 ,
1#
1"
#410000
0"
#415000
0#
1"
#420000
0"
#425000
1"
#430000
0"
#435000
1%
1"
#440000
0"
#445000
0%
1"
#450000
0"
#455000
1"
#460000
0"
#465000
1#
1$
1"
#470000
0"
#475000
0#
0$
1"
#480000
0"
#485000
1"
#490000
0"
#495000
1#
1%
1"
#500000
0"
#505000
0#
0%
1"
#510000
0"
#515000
1"
#520000
0"
#525000
b1 !
b1 +
b1 ,
1$
1"
#530000
0"
#535000
0$
1"
#540000
0"
#545000
1"
#550000
0"
#555000
1#
1%
1"
#560000
0"
#565000
0#
0%
1"
#570000
0"
#575000
1"
#580000
0"
#585000
1#
1$
1%
1"
#590000
0"
#595000
0#
0$
0%
1"
