Basic gates/Buffer_gate/Buffer.v
module Buffer(
    input A,
    output reg Y
);
    always @(*) begin
        Y=A;
    end
endmodule

Basic gates/Buffer_gate/Buffer_tb.v
`timescale 1ns/1ps
`include "Buffer.v"
module Buffer_tb;
    reg A;
    wire y;
    Buffer uut(
        .A(A),
        .Y(y)
    );
    initial begin
        for(integer i=0;i<10;i=i+1) begin
            A = $random;
            #10;
        end
    end
    initial begin
        $monitor("A=%b, Y=%b", A, y);
    end
    initial begin
        $dumpfile("Buffer_tb.vcd");
        $dumpvars(0, Buffer_tb);
    end
endmodule

Basic gates/Buffer_gate/Buffer_tb.vcd
$date
	Mon Mar 23 22:16:10 2026
$end
$version
	Icarus Verilog
$end
$timescale
	1ps
$end
$scope module Buffer_tb $end
$var wire 1 ! y $end
$var reg 1 " A $end
$scope module uut $end
$var wire 1 " A $end
$var reg 1 ! Y $end
$upscope $end
$scope begin $ivl_for_loop0 $end
$var integer 32 # i [31:0] $end
$upscope $end
$upscope $end
$enddefinitions $end
$comment Show the parameter values. $end
$dumpall
$end
#0
$dumpvars
b0 #
0"
0!
$end
#10000
1!
1"
b1 #
#20000
b10 #
#30000
b11 #
#40000
b100 #
#50000
b101 #
#60000
b110 #
#70000
0!
0"
b111 #
#80000
1!
1"
b1000 #
#90000
b1001 #
#100000
b1010 #
